showbackup/__init__.py
showbackup/conf.json
showbackup/example.conf.json
showbackup/logger.py
showbackup/main.py
showbackup/utils.py
showbackup/databases/__init__.py
showbackup/databases/mysql.py
showbackup-0.1.3.dist-info/LICENSE
showbackup-0.1.3.dist-info/METADATA
showbackup-0.1.3.dist-info/WHEEL
showbackup-0.1.3.dist-info/entry_points.txt
showbackup-0.1.3.dist-info/top_level.txt
showbackup-0.1.3.dist-info/RECORD
