Metadata-Version: 2.1
Name: showbackup
Version: 0.1.3
Summary: A MySQL backup tool, Simple, Fast and Powerful. 一个简单，高效，强大的MySQL备份工具。
Home-page: https://github.com/caorongduan/showbackup
Author: caorongduan
Author-email: caorongduan@gmail.com
License: Apache 2.0
Platform: UNKNOWN
Classifier: Development Status :: 4 - Beta
Classifier: Intended Audience :: Developers
Classifier: Topic :: System :: Archiving :: Backup
Classifier: License :: OSI Approved :: Apache Software License
Classifier: Programming Language :: Python :: 3
Classifier: Programming Language :: Python :: 3.3
Classifier: Programming Language :: Python :: 3.4
Classifier: Programming Language :: Python :: 3.5
Classifier: Programming Language :: Python :: 3.6
Classifier: Programming Language :: Python :: 3.7
Classifier: Programming Language :: Python :: 3.8
Requires-Dist: click (==7.1.2)
Requires-Dist: schedule (==0.6.0)
